location_ner/__init__.py
location_ner/cli.py
location_ner/extractor.py
location_ner/fuzzy.py
location_ner/gazetteer.py
location_ner/hf_assisted.py
location_ner/hf_ner.py
location_ner/normalization.py
location_ner/resolver.py
id_location_ner-0.1.0.dist-info/METADATA
id_location_ner-0.1.0.dist-info/WHEEL
id_location_ner-0.1.0.dist-info/entry_points.txt
id_location_ner-0.1.0.dist-info/top_level.txt
id_location_ner-0.1.0.dist-info/RECORD
