Metadata-Version: 2.4
Name: id-location-ner
Version: 0.1.0
Summary: Indonesian location extractor (gazetteer + optional NER)
Author: Gavinda Kinandana
Project-URL: Homepage, https://github.com/vinbyte/id-location-ner
Project-URL: Repository, https://github.com/vinbyte/id-location-ner
Project-URL: Issues, https://github.com/vinbyte/id-location-ner/issues
Requires-Python: >=3.10
Requires-Dist: spacy<4,>=3.7
Requires-Dist: rapidfuzz<4,>=3.6
Provides-Extra: hf
Requires-Dist: transformers>=4.36; extra == "hf"
Requires-Dist: torch>=2.0; extra == "hf"
